literalai/__init__.py
literalai/api.py
literalai/client.py
literalai/context.py
literalai/event_processor.py
literalai/message.py
literalai/my_types.py
literalai/py.typed
literalai/requirements.py
literalai/step.py
literalai/thread.py
literalai/version.py
literalai/wrappers.py
literalai/callback/__init__.py
literalai/callback/langchain_callback.py
literalai/instrumentation/__init__.py
literalai/instrumentation/openai.py
tests/__init__.py
literalai-0.0.101.dist-info/LICENSE
literalai-0.0.101.dist-info/METADATA
literalai-0.0.101.dist-info/WHEEL
literalai-0.0.101.dist-info/top_level.txt
literalai-0.0.101.dist-info/RECORD
