Metadata-Version: 2.1
Name: literalai
Version: 0.0.101
Summary: An SDK for observability in Python applications
Author: 
License-File: LICENSE
Requires-Dist: packaging >=23.0
Requires-Dist: httpx <0.25.0,>=0.23.0
Requires-Dist: pydantic <3,>=1
